{
  "danceability" : 0.861,
  "energy" : 0.647,
  "key" : 7,
  "loudness" : -7.425,
  "mode" : 1,
  "speechiness" : 0.0675,
  "acousticness" : 0.594,
  "instrumentalness" : 0.661,
  "liveness" : 0.114,
  "valence" : 0.670,
  "tempo" : 158.037,
  "type" : "audio_features",
  "id" : "4S4Mfvv03M1cHgIOJcbUCL",
  "uri" : "spotify:track:4S4Mfvv03M1cHgIOJcbUCL",
  "track_href" : "https://api.spotify.com/v1/tracks/4S4Mfvv03M1cHgIOJcbUCL",
  "analysis_url" : "https://api.spotify.com/v1/audio-analysis/4S4Mfvv03M1cHgIOJcbUCL",
  "duration_ms" : 133680,
  "time_signature" : 4
}